excerpt_html.py
excerpt_html-0.2.0.dist-info/LICENSE
excerpt_html-0.2.0.dist-info/METADATA
excerpt_html-0.2.0.dist-info/WHEEL
excerpt_html-0.2.0.dist-info/top_level.txt
excerpt_html-0.2.0.dist-info/RECORD
