Metadata-Version: 2.1
Name: excerpt-html
Version: 0.2.0
Summary: Extract summary from HTML text
Home-page: https://github.com/dairiki/excerpt-html
Author: Jeff Dairiki
Author-email: dairiki@dairiki.org
License: MIT
Keywords: HTML,excerpt,summary
Classifier: Development Status :: 5 - Production/Stable
Classifier: Environment :: Web Environment
Classifier: Intended Audience :: Developers
Classifier: License :: OSI Approved :: MIT License
Classifier: Programming Language :: Python :: 2
Classifier: Programming Language :: Python :: 2.7
Classifier: Programming Language :: Python :: 3
Classifier: Programming Language :: Python :: 3.7
Classifier: Programming Language :: Python :: 3.8
Classifier: Programming Language :: Python :: 3.9
Classifier: Programming Language :: Python :: 3.10
Classifier: Topic :: Software Development :: Libraries :: Python Modules
Classifier: Topic :: Text Processing :: Filters
Classifier: Topic :: Text Processing :: Markup :: HTML
License-File: LICENSE
Requires-Dist: beautifulsoup4 (>=4.4.0)
Requires-Dist: html5lib
